matchart.py
matchart-1.1.5.dist-info/WHEEL
matchart-1.1.5.dist-info/METADATA
matchart-1.1.5.dist-info/RECORD
