Metadata-Version: 2.1
Name: matchart
Version: 1.1.5
Summary: Convenient plotting wrapper around matplotlib.
Keywords: plot,chart,diagram,matplotlib,visualization
Author-email: baterflyrity <baterflyrity@yandex.ru>
Requires-Python: >=3.6
Classifier: Topic :: Scientific/Engineering :: Visualization
Requires-Dist: matplotlib
Requires-Dist: pandas
Requires-Dist: numpy
Project-URL: Home, https://github.com/baterflyrity/matchart
Project-URL: Issues, https://github.com/baterflyrity/matchart/issues
